argolid/pyramid_compositor.py
argolid/_version.py
argolid/__init__.py
argolid/libargolid.cpython-310-darwin.so
argolid/volume_generator.py
argolid/pyramid_generator.py
argolid/.dylibs/libfilepattern.2.dylib
argolid-0.0.7.dist-info/RECORD
argolid-0.0.7.dist-info/WHEEL
argolid-0.0.7.dist-info/top_level.txt
argolid-0.0.7.dist-info/METADATA
argolid-0.0.7.dist-info/licenses/LICENSE
