Metadata-Version: 2.4
Name: argolid
Version: 0.0.7
Summary: Pyramid Generator For OMETiff
Home-page: https://github.com/PolusAI/argolid
Author: Sameeul Bashir Samee
Author-email: sameeul.samee@axleinfo.com
Requires-Python: >=3.8
License-File: LICENSE
Requires-Dist: pydantic
Requires-Dist: filepattern
Requires-Dist: tensorstore
Requires-Dist: bfio
Dynamic: author
Dynamic: author-email
Dynamic: description
Dynamic: description-content-type
Dynamic: home-page
Dynamic: license-file
Dynamic: requires-dist
Dynamic: requires-python
Dynamic: summary
